py_pdf_term/__init__.py
py_pdf_term/_common/__init__.py
py_pdf_term/_common/consts.py
py_pdf_term/_common/data.py
py_pdf_term/_common/utils.py
py_pdf_term/analysis/__init__.py
py_pdf_term/analysis/_analysis/__init__.py
py_pdf_term/analysis/_analysis/concats/__init__.py
py_pdf_term/analysis/_analysis/concats/lr.py
py_pdf_term/analysis/_analysis/cooccurrences/__init__.py
py_pdf_term/analysis/_analysis/cooccurrences/container.py
py_pdf_term/analysis/_analysis/occurrences/__init__.py
py_pdf_term/analysis/_analysis/occurrences/term.py
py_pdf_term/analysis/_analysis/runner.py
py_pdf_term/candidates/__init__.py
py_pdf_term/candidates/_candidates/__init__.py
py_pdf_term/candidates/_candidates/augmenters/__init__.py
py_pdf_term/candidates/_candidates/augmenters/base.py
py_pdf_term/candidates/_candidates/augmenters/combiner.py
py_pdf_term/candidates/_candidates/augmenters/separation.py
py_pdf_term/candidates/_candidates/classifiers/__init__.py
py_pdf_term/candidates/_candidates/classifiers/base.py
py_pdf_term/candidates/_candidates/classifiers/english.py
py_pdf_term/candidates/_candidates/classifiers/japanese.py
py_pdf_term/candidates/_candidates/classifiers/marker.py
py_pdf_term/candidates/_candidates/data.py
py_pdf_term/candidates/_candidates/extractor.py
py_pdf_term/candidates/_candidates/filters/__init__.py
py_pdf_term/candidates/_candidates/filters/combiner.py
py_pdf_term/candidates/_candidates/filters/term/__init__.py
py_pdf_term/candidates/_candidates/filters/term/base.py
py_pdf_term/candidates/_candidates/filters/term/concatenation/__init__.py
py_pdf_term/candidates/_candidates/filters/term/concatenation/english.py
py_pdf_term/candidates/_candidates/filters/term/concatenation/japanese.py
py_pdf_term/candidates/_candidates/filters/term/numeric/__init__.py
py_pdf_term/candidates/_candidates/filters/term/numeric/english.py
py_pdf_term/candidates/_candidates/filters/term/numeric/japanese.py
py_pdf_term/candidates/_candidates/filters/term/propernoun/__init__.py
py_pdf_term-1.2.2.dist-info/LICENSE
py_pdf_term-1.2.2.dist-info/METADATA
py_pdf_term-1.2.2.dist-info/WHEEL
py_pdf_term-1.2.2.dist-info/RECORD
